setup.cfg
setup.py
uarm/__init__.py
uarm/calibrate.py
uarm/uarm.py
uarm4py.egg-info/PKG-INFO
uarm4py.egg-info/SOURCES.txt
uarm4py.egg-info/dependency_links.txt
uarm4py.egg-info/requires.txt
uarm4py.egg-info/top_level.txt