Metadata-Version: 1.0
Name: uarm4py
Version: 1.1.5
Summary: A python library for uArm
Home-page: https://github.com/uarm-developer/uarm4py
Author: Joey Song/Alex Tan
Author-email: developer@ufactory.cc
License: UNKNOWN
Keywords: uarm4py uarm ufactory
Platform: UNKNOWN
